[
    {
      "petId": "dGXf5O9",
      "ownerId": "jcND8dh"
    },
    {
      "petId": "dwW-UfK",
      "ownerId": "jcND8dh"
    },
    {
      "petId": "1p9oPcM",
      "ownerId": "jcND8dh"
    },
    {
      "petId": "dGXf5O9",
      "ownerId": "434AFaI"
    },
    {
      "petId": "dwW-UfK",
      "ownerId": "434AFaI"
    },
    {
      "petId": "1p9oPcM",
      "ownerId": "434AFaI"
    },
    {
      "petId": "s7xFnQQ",
      "ownerId": "mqxpOYo"
    },
    {
      "petId": "Ccixu3v",
      "ownerId": "6Vk_v-K"
    },
    {
      "petId": "6hIG0NE",
      "ownerId": "5IHHxTh"
    },
    {
      "petId": "Lh7diV3",
      "ownerId": "7-EsZ1L"
    },
    {
      "petId": "O5-KMSE",
      "ownerId": "eRgVMZd"
    },
    {
      "petId": "UUy2epG",
      "ownerId": "oo24Rwi"
    },
    {
      "petId": "LuIjiF7",
      "ownerId": "pvjwV4H"
    },
    {
      "petId": "Ricah2a",
      "ownerId": "I4DIbFj"
    },
    {
      "petId": "iqL33Eh",
      "ownerId": "A2ZnfcQ"
    },
    {
      "petId": "fiQ_EZE",
      "ownerId": "gjeIFfQ"
    },
    {
      "petId": "Jp0ZQqU",
      "ownerId": "jntFHeu"
    },
    {
      "petId": "8sdMh5q",
      "ownerId": "0BCzzTb"
    },
    {
      "petId": "jI3RVEU",
      "ownerId": "2aV48vN"
    },
    {
      "petId": "3jVKsTR",
      "ownerId": "mulFazh"
    },
    {
      "petId": "gIR858c",
      "ownerId": "wOMrp93"
    },
    {
      "petId": "HeoSm9V",
      "ownerId": "Z8KvwLX"
    },
    {
      "petId": "BTNrkbC",
      "ownerId": "jWc74nH"
    },
    {
      "petId": "BTNrkbC",
      "ownerId": "Z8KvwLX"
    },
    {
      "petId": "HeoSm9V",
      "ownerId": "jWc74nH"
    }
  ]